setup.py
jsonalyzer/__init__.py
jsonalyzer/callbacks.py
jsonalyzer/cmdline.py
jsonalyzer/defaults.py
jsonalyzer/utils.py
jsonalyzer.egg-info/PKG-INFO
jsonalyzer.egg-info/SOURCES.txt
jsonalyzer.egg-info/dependency_links.txt
jsonalyzer.egg-info/entry_points.txt
jsonalyzer.egg-info/requires.txt
jsonalyzer.egg-info/top_level.txt