Metadata-Version: 1.0
Name: jsonalyzer
Version: 0.0.4
Summary: Write callbacks for anlayzing json
Home-page: https://github.com/saurabh-hirani/jsonalyzer
Author: Saurabh Hirani
Author-email: saurabh.hirani@gmail.com
License: MIT
Platform: UNKNOWN
